ipyturtle2/__init__.py
ipyturtle2/_frontend.py
ipyturtle2/_version.py
ipyturtle2/example.py
ipyturtle2/labextension/ipyturtle2-0.6.0.tgz
ipyturtle2/labextension/ipyturtle2-0.7.0.tgz
ipyturtle2/labextension/ipyturtle2-0.7.1.tgz
ipyturtle2/labextension/ipyturtle2-0.7.2.tgz
ipyturtle2/labextension/ipyturtle2-0.7.3.tgz
ipyturtle2/labextension/ipyturtle2-0.7.4.tgz
ipyturtle2/labextension/ipyturtle2-0.7.5.tgz
ipyturtle2/labextension/ipyturtle2-0.8.0.tgz
ipyturtle2/labextension/ipyturtle2-0.8.1.tgz
ipyturtle2/nbextension/__init__.py
ipyturtle2/nbextension/static/extension.js
ipyturtle2/nbextension/static/index.js
ipyturtle2/nbextension/static/index.js.map
ipyturtle2/tests/__init__.py
ipyturtle2/tests/conftest.py
ipyturtle2/tests/test_example.py
ipyturtle2/tests/test_nbextension_path.py
ipyturtle2-0.8.1.data/data/etc/jupyter/nbconfig/notebook.d/ipyturtle2.json
ipyturtle2-0.8.1.data/data/share/jupyter/lab/extensions/ipyturtle2-0.8.1.tgz
ipyturtle2-0.8.1.data/data/share/jupyter/nbextensions/ipyturtle2/extension.js
ipyturtle2-0.8.1.data/data/share/jupyter/nbextensions/ipyturtle2/index.js
ipyturtle2-0.8.1.data/data/share/jupyter/nbextensions/ipyturtle2/index.js.map
ipyturtle2-0.8.1.dist-info/LICENSE.txt
ipyturtle2-0.8.1.dist-info/METADATA
ipyturtle2-0.8.1.dist-info/WHEEL
ipyturtle2-0.8.1.dist-info/top_level.txt
ipyturtle2-0.8.1.dist-info/RECORD
